ma_utils/__init__.py
ma_utils/rank_array_adapter.py
ma_utils-0.0.3.dist-info/METADATA
ma_utils-0.0.3.dist-info/WHEEL
ma_utils-0.0.3.dist-info/licenses/LICENSE
ma_utils-0.0.3.dist-info/RECORD
