Metadata-Version: 2.4
Name: ma-utils
Version: 0.0.3
Summary: Various assorted utilities for meta analysis workflows.
Project-URL: Repository, https://github.com/jordantgh/ma-utils
Author-email: Jordan Taylor <jtaylor81284@gmail.com>
License-File: LICENSE
Keywords: python
Classifier: Intended Audience :: Developers
Classifier: Programming Language :: Python
Classifier: Programming Language :: Python :: 3
Classifier: Programming Language :: Python :: 3.9
Classifier: Programming Language :: Python :: 3.10
Classifier: Programming Language :: Python :: 3.11
Classifier: Programming Language :: Python :: 3.12
Classifier: Programming Language :: Python :: 3.13
Classifier: Topic :: Software Development :: Libraries :: Python Modules
Requires-Python: <4.0,>=3.11
Requires-Dist: numpy==2.2.3
Requires-Dist: pandas>=2.1.0
